pytdx2/__init__.py
pytdx2/base_socket_client.py
pytdx2/errors.py
pytdx2/exhq.py
pytdx2/heartbeat.py
pytdx2/helper.py
pytdx2/hq.py
pytdx2/log.py
pytdx2/params.py
pytdx2/bin/__init__.py
pytdx2/bin/get_tdx_trader_server.py
pytdx2/bin/hqbenchmark.py
pytdx2/bin/hqget.py
pytdx2/bin/hqreader.py
pytdx2/config/__init__.py
pytdx2/config/hosts.py
pytdx2/crawler/__init__.py
pytdx2/crawler/base_crawler.py
pytdx2/crawler/history_financial_crawler.py
pytdx2/parser/__init__.py
pytdx2/parser/base.py
pytdx2/parser/ex_get_history_instrument_bars_range.py
pytdx2/parser/ex_get_history_minute_time_data.py
pytdx2/parser/ex_get_history_transaction_data.py
pytdx2/parser/ex_get_instrument_bars.py
pytdx2/parser/ex_get_instrument_count.py
pytdx2/parser/ex_get_instrument_info.py
pytdx2/parser/ex_get_instrument_quote.py
pytdx2/parser/ex_get_instrument_quote_list.py
pytdx2/parser/ex_get_markets.py
pytdx2/parser/ex_get_minute_time_data.py
pytdx2/parser/ex_get_transaction_data.py
pytdx2/parser/ex_setup_commands.py
pytdx2/parser/get_block_info.py
pytdx2/parser/get_company_info_category.py
pytdx2/parser/get_company_info_content.py
pytdx2/parser/get_finance_info.py
pytdx2/parser/get_history_minute_time_data.py
pytdx2/parser/get_history_transaction_data.py
pytdx2/parser/get_index_bars.py
pytdx2/parser/get_minute_time_data.py
pytdx2/parser/get_report_file.py
pytdx2/parser/get_security_bars.py
pytdx2/parser/get_security_count.py
pytdx2/parser/get_security_list.py
pytdx2/parser/get_security_quotes.py
pytdx2/parser/get_transaction_data.py
pytdx2/parser/get_xdxr_info.py
pytdx2/parser/raw_parser.py
pytdx2/parser/setup_commands.py
pytdx2/pool/__init__.py
pytdx2/pool/hqpool.py
pytdx2/pool/ippool.py
pytdx2/reader/__init__.py
pytdx2/reader/base_reader.py
pytdx2/reader/block_reader.py
pytdx2/reader/daily_bar_reader.py
pytdx2/reader/exhq_daily_bar_reader.py
pytdx2/reader/gbbq_reader.py
pytdx2/reader/history_financial_reader.py
pytdx2/reader/lc_min_bar_reader.py
pytdx2/reader/min_bar_reader.py
pytdx2-1.72.dist-info/METADATA
pytdx2-1.72.dist-info/WHEEL
pytdx2-1.72.dist-info/entry_points.txt
pytdx2-1.72.dist-info/top_level.txt
pytdx2-1.72.dist-info/RECORD
