Metadata-Version: 2.1
Name: pytdx2
Version: 1.72
Summary: A Python Interface to TDX protocol
Home-page: https://github.com/wenxingxing/pytdx
Author: ['RainX<Jing Xu>', 'yutiansut']
Author-email: i@rainx.cc
License: UNKNOWN
Platform: UNKNOWN
Requires-Dist: click
Requires-Dist: pandas
Requires-Dist: six
Requires-Dist: cryptography
